[
    {
        "key": "data/config/contact_tag_data.json$.military.name",
        "original": "Military",
        "translation": "军方",
        "stage": 5,
        "context": "版本：0.98-RC8 词条格式：v2\n源文件：data\\config\\contact_tag_data.json\n数据路径：$.military.name"
    },
    {
        "key": "data/config/contact_tag_data.json$.pather.name",
        "original": "Pather",
        "translation": "左径",
        "stage": 5,
        "context": "版本：0.98-RC8 词条格式：v2\n源文件：data\\config\\contact_tag_data.json\n数据路径：$.pather.name"
    },
    {
        "key": "data/config/contact_tag_data.json$.science.name",
        "original": "Science",
        "translation": "科研",
        "stage": 5,
        "context": "版本：0.98-RC8 词条格式：v2\n源文件：data\\config\\contact_tag_data.json\n数据路径：$.science.name"
    },
    {
        "key": "data/config/contact_tag_data.json$.trade.name",
        "original": "Trade",
        "translation": "贸易",
        "stage": 5,
        "context": "版本：0.98-RC8 词条格式：v2\n源文件：data\\config\\contact_tag_data.json\n数据路径：$.trade.name"
    },
    {
        "key": "data/config/contact_tag_data.json$.underworld.name",
        "original": "Underworld",
        "translation": "黑帮",
        "stage": 5,
        "context": "版本：0.98-RC8 词条格式：v2\n源文件：data\\config\\contact_tag_data.json\n数据路径：$.underworld.name"
    }
]