[
    {
        "key": "data/shipsystems/scripts/AmmoFeedStats.java#\"ballistic flux use -\"",
        "original": "ballistic flux use -",
        "translation": "实弹武器幅能产生 -",
        "stage": 1,
        "context": "版本：0.98-RC8 词条格式：v2\n文件：data/shipsystems/scripts/AmmoFeedStats.java\n源码序号：2\n原始数据：\"ballistic flux use -\"\n译文数据：\"实弹武器幅能产生 -\""
    },
    {
        "key": "data/shipsystems/scripts/AmmoFeedStats.java#\"ballistic rate of fire +\"",
        "original": "ballistic rate of fire +",
        "translation": "实弹武器射速 +",
        "stage": 1,
        "context": "版本：0.98-RC8 词条格式：v2\n文件：data/shipsystems/scripts/AmmoFeedStats.java\n源码序号：0\n原始数据：\"ballistic rate of fire +\"\n译文数据：\"实弹武器射速 +\""
    }
]